saintcord/__init__.py
egirl-1.0.dist-info/METADATA
egirl-1.0.dist-info/WHEEL
egirl-1.0.dist-info/top_level.txt
egirl-1.0.dist-info/RECORD
