Metadata-Version: 2.2
Name: egirl
Version: 1.0
Summary: Official @saint#7089 wrapper for Discord API.
Author: Saint Official
Author-email: support@saint.dev
Requires-Python: >=3.8
Requires-Dist: discord.py
Dynamic: author
Dynamic: author-email
Dynamic: requires-dist
Dynamic: requires-python
Dynamic: summary
